lolclient/__init__.py
lolclient/champselect.py
lolclient/client.py
lolclient/lobby.py
lolclient/lockfile.py
lolclient/request.py
lolclient_lib-0.0.4.dist-info/LICENSE
lolclient_lib-0.0.4.dist-info/METADATA
lolclient_lib-0.0.4.dist-info/WHEEL
lolclient_lib-0.0.4.dist-info/top_level.txt
lolclient_lib-0.0.4.dist-info/RECORD
